setup.py
PyPreval.egg-info/PKG-INFO
PyPreval.egg-info/SOURCES.txt
PyPreval.egg-info/dependency_links.txt
PyPreval.egg-info/top_level.txt
PyPreval.egg-info/zip-safe
pypreval/__init__.py
pypreval/nulllock.py
pypreval/store.py
pypreval/test_store.py
pypreval/test_util.py
pypreval/util.py
