Metadata-Version: 1.0
Name: PyPreval
Version: 0.0.0
Summary: object prevalence service
Home-page: UNKNOWN
Author: Andreas Kostyrka
Author-email: andreas@kostyrka.org
License: UNKNOWN
Platform: any
Classifier: Development Status :: 3 - Alpha
Classifier: Topic :: Database :: Database Engines/Servers
Classifier: Programming Language :: Python
Classifier: Operating System :: OS Independent
Classifier: License :: OSI Approved :: GNU Library or Lesser General Public License (LGPL)
Classifier: Intended Audience :: Developers
